python_web_exceptions/_400.py
python_web_exceptions/_500.py
python_web_exceptions/__init__.py
python_web_exceptions/base_http_exception.py
python_web_exceptions-1.1.dist-info/LICENSE
python_web_exceptions-1.1.dist-info/METADATA
python_web_exceptions-1.1.dist-info/WHEEL
python_web_exceptions-1.1.dist-info/top_level.txt
python_web_exceptions-1.1.dist-info/RECORD
