Metadata-Version: 2.1
Name: python-web-exceptions
Version: 1.1
Summary: Framework agnostic web exceptions for python
Home-page: https://github.com/ajmar3/python-web-exceptions
Author: Aaron Martin
Author-email: UNKNOWN
License: MIT
Platform: UNKNOWN
